Workbook

Sheet Sheet4
A1: Table | B1: Delete Export count | D1: EXP LOG count | F1: Count Compare
A2: PS_AP_ARC_BCH_XR_H | B2: 0 | D2: =IF(COUNTIF(Sheet2!A:A,A2)>0,VLOOKUP(A2,Sheet2!A:B,2,FALSE),"Not Found") -> 0 | F2: =IF(B2=D2,"matching","not Matching") -> matching
A3: PS_AP_ARC_DIST_L_H | B3: 1124091 | D3: =IF(COUNTIF(Sheet2!A:A,A3)>0,VLOOKUP(A3,Sheet2!A:B,2,FALSE),"Not Found") -> 1124091 | F3: =IF(B3=D3,"matching","not Matching") -> matching
A4: PS_AP_ARC_DIST_N_H | B4: 0 | D4: =IF(COUNTIF(Sheet2!A:A,A4)>0,VLOOKUP(A4,Sheet2!A:B,2,FALSE),"Not Found") -> 0 | F4: =IF(B4=D4,"matching","not Matching") -> matching
A5: PS_AP_ARC_EXP_DL_H | B5: 0 | D5: =IF(COUNTIF(Sheet2!A:A,A5)>0,VLOOKUP(A5,Sheet2!A:B,2,FALSE),"Not Found") -> 0 | F5: =IF(B5=D5,"matching","not Matching") -> matching
A6: PS_AP_ARC_PY_MSG_H | B6: 20 | D6: =IF(COUNTIF(Sheet2!A:A,A6)>0,VLOOKUP(A6,Sheet2!A:B,2,FALSE),"Not Found") -> 20 | F6: =IF(B6=D6,"matching","not Matching") -> matching
A7: PS_AP_ARC_PYM_AD_H | B7: 442649 | D7: =IF(COUNTIF(Sheet2!A:A,A7)>0,VLOOKUP(A7,Sheet2!A:B,2,FALSE),"Not Found") -> 442649 | F7: =IF(B7=D7,"matching","not Matching") -> matching
A8: PS_AP_ARC_PYM_RC_H | B8: 403197 | D8: =IF(COUNTIF(Sheet2!A:A,A8)>0,VLOOKUP(A8,Sheet2!A:B,2,FALSE),"Not Found") -> 403197 | F8: =IF(B8=D8,"matching","not Matching") -> matching
A9: PS_AP_ARC_PYM_TB_H | B9: 402580 | D9: =IF(COUNTIF(Sheet2!A:A,A9)>0,VLOOKUP(A9,Sheet2!A:B,2,FALSE),"Not Found") -> 402580 | F9: =IF(B9=D9,"matching","not Matching") -> matching
A10: PS_AP_ARC_PYM_WT_H | B10: 19568 | D10: =IF(COUNTIF(Sheet2!A:A,A10)>0,VLOOKUP(A10,Sheet2!A:B,2,FALSE),"Not Found") -> 19568 | F10: =IF(B10=D10,"matching","not Matching") -> matching
A11: PS_AP_ARC_PYM_XR_H | B11: 579392 | D11: =IF(COUNTIF(Sheet2!A:A,A11)>0,VLOOKUP(A11,Sheet2!A:B,2,FALSE),"Not Found") -> 579392 | F11: =IF(B11=D11,"matching","not Matching") -> matching
A12: PS_AP_ARC_VCH_AC_H | B12: 5181089 | D12: =IF(COUNTIF(Sheet2!A:A,A12)>0,VLOOKUP(A12,Sheet2!A:B,2,FALSE),"Not Found") -> 5181089 | F12: =IF(B12=D12,"matching","not Matching") -> matching
A13: PS_AP_ARC_VCH_DO_H | B13: 0 | D13: =IF(COUNTIF(Sheet2!A:A,A13)>0,VLOOKUP(A13,Sheet2!A:B,2,FALSE),"Not Found") -> 0 | F13: =IF(B13=D13,"matching","not Matching") -> matching
... A543: PS_WTHD_UPDT_H_XX | B543: 0 | D543: =IF(COUNTIF(Sheet2!A:A,A543)>0,VLOOKUP(A543,Sheet2!A:B,2,FALSE),"Not Found") -> 0 | F543: =IF(B543=D543,"matching","not Matching") -> matching
A544: (blank)
A545: Grand Total | B545: 155039757 | D545: =SUM(D2:D543) -> 155039757

Sheet Sheet1
A1: Table Name | B1: Count | F1: Count on sheet 2 | H1: Count Compare
A2: PS_WTH_TRXTBL_H_XX | B2: 14674 | D2: (PSARCH_ID=APPYMTXX, | E2: PSARCH_BATCHNUM=93). | H2: =IF(B2=F2,"matching","not Matching") -> not Matching
A3: PS_AP_ARC_DIST_N_H | B3: 0 | D3: (PSARCH_ID=APVCHRXX, | E3: PSARCH_BATCHNUM=100). | F3: =IF(COUNTIF(Sheet2!A:A,A3)>0,VLOOKUP(A3,Sheet2!A:B,2,FALSE),"Not Found") -> 0 | H3: =IF(B3=F3,"matching","not Matching") -> matching
A4: PS_REMRPRT_H_XX | B4: 0 | D4: (PSARCH_ID=APVCHRXX, | E4: PSARCH_BATCHNUM=100). | F4: =IF(COUNTIF(Sheet2!A:A,A4)>0,VLOOKUP(A4,Sheet2!A:B,2,FALSE),"Not Found") -> 0 | H4: =IF(B4=F4,"matching","not Matching") -> matching
A5: PS_APYX42_IFC_H_XX | B5: 0 | D5: (PSARCH_ID=APY42_XX, | E5: PSARCH_BATCHNUM=102). | F5: =IF(COUNTIF(Sheet2!A:A,A5)>0,VLOOKUP(A5,Sheet2!A:B,2,FALSE),"Not Found") -> 0 | H5: =IF(B5=F5,"matching","not Matching") -> matching
A6: PS_AR_FRMLIN2_XX_H | B6: 0 | D6: (PSARCH_ID=ARBUR_XX, | E6: PSARCH_BATCHNUM=97). | F6: =IF(COUNTIF(Sheet2!A:A,A6)>0,VLOOKUP(A6,Sheet2!A:B,2,FALSE),"Not Found") -> 0 | H6: =IF(B6=F6,"matching","not Matching") -> matching
A7: PS_AR_FRMLIN3_XX_H | B7: 0 | D7: (PSARCH_ID=ARBUR_XX, | E7: PSARCH_BATCHNUM=97). | F7: =IF(COUNTIF(Sheet2!A:A,A7)>0,VLOOKUP(A7,Sheet2!A:B,2,FALSE),"Not Found") -> 0 | H7: =IF(B7=F7,"matching","not Matching") -> matching
A8: PS_AR_ITM_ACTXDT_H | B8: 0 | D8: (PSARCH_ID=ARITEM, | E8: PSARCH_BATCHNUM=98). | F8: =IF(COUNTIF(Sheet2!A:A,A8)>0,VLOOKUP(A8,Sheet2!A:B,2,FALSE),"Not Found") -> 0 | H8: =IF(B8=F8,"matching","not Matching") -> matching
A9: PS_AR_ITMDSP_XX_H | B9: 0 | D9: (PSARCH_ID=ARITEM, | E9: PSARCH_BATCHNUM=98). | F9: =IF(COUNTIF(Sheet2!A:A,A9)>0,VLOOKUP(A9,Sheet2!A:B,2,FALSE),"Not Found") -> 0 | H9: =IF(B9=F9,"matching","not Matching") -> matching
A10: PS_AR_PEND_VAT_H | B10: 0 | D10: (PSARCH_ID=ARPEND, | E10: PSARCH_BATCHNUM=96). | F10: =IF(COUNTIF(Sheet2!A:A,A10)>0,VLOOKUP(A10,Sheet2!A:B,2,FALSE),"Not Found") -> 0 | H10: =IF(B10=F10,"matching","not Matching") -> matching
A11: PS_AR_PO_SEQ_XX_H | B11: 0 | D11: (PSARCH_ID=ARPO_XX, | E11: PSARCH_BATCHNUM=72). | F11: =IF(COUNTIF(Sheet2!A:A,A11)>0,VLOOKUP(A11,Sheet2!A:B,2,FALSE),"Not Found") -> 0 | H11: =IF(B11=F11,"matching","not Matching") -> matching
A12: PS_AR_PAYMENT_H | B12: 1335452 | D12: (PSARCH_ID=ARPYMT, | E12: PSARCH_BATCHNUM=1). | F12: =IF(COUNTIF(Sheet2!A:A,A12)>0,VLOOKUP(A12,Sheet2!A:B,2,FALSE),"Not Found") -> 1335452 | H12: =IF(B12=F12,"matching","not Matching") -> matching
A13: PS_AR_PAY_ITEM_H | B13: 0 | D13: (PSARCH_ID=ARPYMT, | E13: PSARCH_BATCHNUM=1). | F13: =IF(COUNTIF(Sheet2!A:A,A13)>0,VLOOKUP(A13,Sheet2!A:B,2,FALSE),"Not Found") -> 0 | H13: =IF(B13=F13,"matching","not Matching") -> matching
A14: PS_AR_PAY_IT_MRL_H | B14: 0 | D14: (PSARCH_ID=ARPYMT, | E14: PSARCH_BATCHNUM=1). | F14: =IF(COUNTIF(Sheet2!A:A,A14)>0,VLOOKUP(A14,Sheet2!A:B,2,FALSE),"Not Found") -> 0 | H14: =IF(B14=F14,"matching","not Matching") -> matching
... A617: PS_PO_LN_SHIP_H_XX | B617: 0 | D617: (PSARCH_ID=PUR_POXX, | E617: PSARCH_BATCHNUM=10). | F617: =IF(COUNTIF(Sheet2!A:A,A617)>0,VLOOKUP(A617,Sheet2!A:B,2,FALSE),"Not Found") -> 0 | H617: =IF(B617=F617,"matching","not Matching") -> matching

Sheet Sheet2
A1: History Records (EXP LOG) | B1: Counts
A2: PS_AP_ARC_BCH_XR_H | B2: 0
A3: PS_AP_ARC_DIST_L_H | B3: 1124091
A4: PS_AP_ARC_DIST_N_H | B4: 0
A5: PS_AP_ARC_EXP_DL_H | B5: 0
A6: PS_AP_ARC_PY_MSG_H | B6: 20
A7: PS_AP_ARC_PYM_AD_H | B7: 442649
A8: PS_AP_ARC_PYM_RC_H | B8: 403197
A9: PS_AP_ARC_PYM_TB_H | B9: 402580
A10: PS_AP_ARC_PYM_WT_H | B10: 19568
A11: PS_AP_ARC_PYM_XR_H | B11: 579392
A12: PS_AP_ARC_VCH_AC_H | B12: 5181089
A13: PS_AP_ARC_VCH_DO_H | B13: 0
... A543: PS_WTHD_UPDT_H_XX | B543: 0
