Workbook

Sheet Sheet1
A1: Table Name | B1: Count | C1: Temp | D1: Batch no. | F1: Table name | G1: Export Count | I1: Export Count | J1: Count Compare
A2: PS_EOAWSTPINST_HXX | B2: 0 | C2: ABSAPRXX | D2: 69 | F2: PS_ADD_PAY_EFFDT_H | G2: 0 | I2: =IF(COUNTIF(Sheet2!A:A,F2)>0,VLOOKUP(F2,Sheet2!A:B,2,FALSE),"Not Found") -> 0 | J2: =IF(G2=I2,"Matching","Mis Match") -> Matching
A3: PS_EOAW_SUMM_HXX | B3: 0 | C3: ABSAPRXX | D3: 69 | F3: PS_ADD_PAY_ERNCD_H | G3: 0 | I3: =IF(COUNTIF(Sheet2!A:A,F3)>0,VLOOKUP(F3,Sheet2!A:B,2,FALSE),"Not Found") -> 0 | J3: =IF(G3=I3,"Matching","Mis Match") -> Matching
A4: PS_EOAW_WL_HXX | B4: 0 | C4: ABSAPRXX | D4: 69 | F4: PS_ADD_PY_DRW_H_XX | G4: 0 | I4: =IF(COUNTIF(Sheet2!A:A,F4)>0,VLOOKUP(F4,Sheet2!A:B,2,FALSE),"Not Found") -> 0 | J4: =IF(G4=I4,"Matching","Mis Match") -> Matching
A5: PS_GP_ABSSXREF_HXX | B5: 0 | C5: ABSAPRXX | D5: 69 | F5: PS_ADDL_PAY_DATA_H | G5: 0 | I5: =IF(COUNTIF(Sheet2!A:A,F5)>0,VLOOKUP(F5,Sheet2!A:B,2,FALSE),"Not Found") -> 0 | J5: =IF(G5=I5,"Matching","Mis Match") -> Matching
A6: PS_GP_ABS_FCST_HXX | B6: 0 | C6: ABSFCSXX | D6: 70 | F6: PS_ADDRESSES_H_XX | G6: 0 | I6: =IF(COUNTIF(Sheet2!A:A,F6)>0,VLOOKUP(F6,Sheet2!A:B,2,FALSE),"Not Found") -> 0 | J6: =IF(G6=I6,"Matching","Mis Match") -> Matching
A7: PS_BL_ADJ_CN_TAX_H | B7: 0 | C7: ADJ_C_XX | D7: 5 | F7: PS_AUDITTLRTS_H_XX | G7: 0 | I7: =IF(COUNTIF(Sheet2!A:A,F7)>0,VLOOKUP(F7,Sheet2!A:B,2,FALSE),"Not Found") -> 0 | J7: =IF(G7=I7,"Matching","Mis Match") -> Matching
A8: PS_BN_DEMG_WK_H_XX | B8: 4261 | C8: BEN5_XX | D8: 11 | F8: PS_BAL_ADJ_CHK_H | G8: 54 | I8: =IF(COUNTIF(Sheet2!A:A,F8)>0,VLOOKUP(F8,Sheet2!A:B,2,FALSE),"Not Found") -> 54 | J8: =IF(G8=I8,"Matching","Mis Match") -> Matching
A9: PS_BNX75_GEN_H_XX | B9: 0 | C9: BEN75_XX | D9: 18 | F9: PS_BAL_ADJ_DED_H | G9: 18 | I9: =IF(COUNTIF(Sheet2!A:A,F9)>0,VLOOKUP(F9,Sheet2!A:B,2,FALSE),"Not Found") -> 18 | J9: =IF(G9=I9,"Matching","Mis Match") -> Matching
A10: PS_DISABILTY_BEN_H | B10: 0 | C10: BEN8_XX | D10: 14 | F10: PS_BAL_ADJ_ERN_H | G10: 40 | I10: =IF(COUNTIF(Sheet2!A:A,F10)>0,VLOOKUP(F10,Sheet2!A:B,2,FALSE),"Not Found") -> 40 | J10: =IF(G10=I10,"Matching","Mis Match") -> Matching
A11: PS_BNX74_STG_H_XX | B11: 0 | C11: BENX_74 | D11: 17 | F11: PS_BAL_ADJ_TAX_H | G11: 183 | I11: =IF(COUNTIF(Sheet2!A:A,F11)>0,VLOOKUP(F11,Sheet2!A:B,2,FALSE),"Not Found") -> 183 | J11: =IF(G11=I11,"Matching","Mis Match") -> Matching
A12: PS_BNX74_GEN_H_XX | B12: 0 | C12: BENX_74 | D12: 17 | F12: PS_BEN_LVSP_H_XX | G12: 481505 | I12: =IF(COUNTIF(Sheet2!A:A,F12)>0,VLOOKUP(F12,Sheet2!A:B,2,FALSE),"Not Found") -> 481505 | J12: =IF(G12=I12,"Matching","Mis Match") -> Matching
A13: PS_SCK_SPO_HR_H_XX | B13: 0 | C13: BSC17_XX | D13: 36 | F13: PS_BEN_PRGPRTC_HXX | G13: 0 | I13: =IF(COUNTIF(Sheet2!A:A,F13)>0,VLOOKUP(F13,Sheet2!A:B,2,FALSE),"Not Found") -> 0 | J13: =IF(G13=I13,"Matching","Mis Match") -> Matching
... A358: PS_PERSNIDEXP_H_XX | B358: 0 | C358: PSPER_XX | D358: 79 | F358: PS_VISAPMTSUP_H_XX | G358: 0 | I358: =IF(COUNTIF(Sheet2!A:A,F358)>0,VLOOKUP(F358,Sheet2!A:B,2,FALSE),"Not Found") -> 0 | J358: =IF(G358=I358,"Matching","Mis Match") -> Matching
A359: PS_PERX33700T_H_XX | B359: 0 | C359: PSPER_XX | D359: 79 | F359: (blank) | I359: =IF(COUNTIF(Sheet2!A:A,F359)>0,VLOOKUP(F359,Sheet2!A:B,2,FALSE),"Not Found") -> 0 | J359: =IF(G359=I359,"Matching","Mis Match") -> Matching
A360: PS_PRIORWORKE_H_XX | B360: 0 | C360: PSPER_XX | D360: 79 | F360: Grand Total | G360: 136326574
A361: PS_TAX_DISTRIB_H | B361: 0 | C361: PSPER_XX | D361: 79
A362: PS_PERSDATAXX_H_XX | B362: 0 | C362: PSPER_XX | D362: 79
A363: PS_PRIORWORKS_H_XX | B363: 0 | C363: PSPER_XX | D363: 79
A364: PS_EOAW_HISCOM_HXX | B364: 0 | C364: TLEOA_XX | D364: 62
A365: PS_TL_MEALAUD_H_XX | B365: 0 | C365: TLMEL_XX | D365: 53
A366: PS_OB_ATTACH_H_XX | B366: 0 | C366: TLOB_XX | D366: 54
A367: PS_TL_EXCEPTN_HST | B367: 0 | C367: TLEXCPXX | D367: 56
A368: PS_TL_RTS_TRC_H_XX | B368: 0 | C368: TLRTS_XX | D368: 55
A369: PS_TLTRCOMNT_H_XX | B369: 0 | C369: TLTRC_XX | D369: 60

Sheet Generic 2
A1: Table Name | B1: Delete Count | D1: Table Name | E1: Count | H1: PRD EXPORT COUNT | I1: Count Compare
A2: PS_ADD_PAY_EFFDT_H | B2: 0 | D2: PS_EOAWSTPINST_HXX | E2: 0 | F2: ABSAPRXX, | G2: 69 | H2: =IF(COUNTIF(Sheet2!A:A,A2)>0,VLOOKUP(A2,Sheet2!A:B,2,FALSE),"Not Found") -> 0 | I2: =IF(B2=H2,"Match","Mis Match") -> Match
A3: PS_ADD_PAY_ERNCD_H | B3: 0 | D3: PS_EOAW_SUMM_HXX | E3: 0 | F3: ABSAPRXX, | G3: 69 | H3: =IF(COUNTIF(Sheet2!A:A,A3)>0,VLOOKUP(A3,Sheet2!A:B,2,FALSE),"Not Found") -> 0 | I3: =IF(B3=H3,"Match","Mis Match") -> Match
A4: PS_ADD_PY_DRW_H_XX | B4: 0 | D4: PS_EOAW_WL_HXX | E4: 0 | F4: ABSAPRXX, | G4: 69 | H4: =IF(COUNTIF(Sheet2!A:A,A4)>0,VLOOKUP(A4,Sheet2!A:B,2,FALSE),"Not Found") -> 0 | I4: =IF(B4=H4,"Match","Mis Match") -> Match
A5: PS_ADDL_PAY_DATA_H | B5: 0 | D5: PS_GP_ABSSXREF_HXX | E5: 0 | F5: ABSAPRXX, | G5: 69 | H5: =IF(COUNTIF(Sheet2!A:A,A5)>0,VLOOKUP(A5,Sheet2!A:B,2,FALSE),"Not Found") -> 0 | I5: =IF(B5=H5,"Match","Mis Match") -> Match
A6: PS_ADDRESSES_H_XX | B6: 0 | D6: PS_GP_ABS_FCST_HXX | E6: 0 | F6: ABSFCSXX, | G6: 70 | H6: =IF(COUNTIF(Sheet2!A:A,A6)>0,VLOOKUP(A6,Sheet2!A:B,2,FALSE),"Not Found") -> 0 | I6: =IF(B6=H6,"Match","Mis Match") -> Match
A7: PS_AUDITTLRTS_H_XX | B7: 0 | D7: PS_BL_ADJ_CN_TAX_H | E7: 0 | F7: ADJ_C_XX, | G7: 5 | H7: =IF(COUNTIF(Sheet2!A:A,A7)>0,VLOOKUP(A7,Sheet2!A:B,2,FALSE),"Not Found") -> 0 | I7: =IF(B7=H7,"Match","Mis Match") -> Match
A8: PS_BAL_ADJ_CHK_H | B8: 54 | D8: PS_BN_DEMG_WK_H_XX | E8: 4261 | F8: BEN5_XX, | G8: 11 | H8: =IF(COUNTIF(Sheet2!A:A,A8)>0,VLOOKUP(A8,Sheet2!A:B,2,FALSE),"Not Found") -> 54 | I8: =IF(B8=H8,"Match","Mis Match") -> Match
A9: PS_BAL_ADJ_DED_H | B9: 18 | D9: PS_BNX75_GEN_H_XX | E9: 0 | F9: BEN75_XX, | G9: 18 | H9: =IF(COUNTIF(Sheet2!A:A,A9)>0,VLOOKUP(A9,Sheet2!A:B,2,FALSE),"Not Found") -> 18 | I9: =IF(B9=H9,"Match","Mis Match") -> Match
A10: PS_BAL_ADJ_ERN_H | B10: 40 | D10: PS_DISABILTY_BEN_H | E10: 0 | F10: BEN8_XX, | G10: 14 | H10: =IF(COUNTIF(Sheet2!A:A,A10)>0,VLOOKUP(A10,Sheet2!A:B,2,FALSE),"Not Found") -> 40 | I10: =IF(B10=H10,"Match","Mis Match") -> Match
A11: PS_BAL_ADJ_TAX_H | B11: 183 | D11: PS_BNX74_STG_H_XX | E11: 0 | F11: BENX_74, | G11: 17 | H11: =IF(COUNTIF(Sheet2!A:A,A11)>0,VLOOKUP(A11,Sheet2!A:B,2,FALSE),"Not Found") -> 183 | I11: =IF(B11=H11,"Match","Mis Match") -> Match
A12: PS_BEN_LVSP_H_XX | B12: 481505 | D12: PS_BNX74_GEN_H_XX | E12: 0 | F12: BENX_74, | G12: 17 | H12: =IF(COUNTIF(Sheet2!A:A,A12)>0,VLOOKUP(A12,Sheet2!A:B,2,FALSE),"Not Found") -> 481505 | I12: =IF(B12=H12,"Match","Mis Match") -> Match
A13: PS_BEN_PRGPRTC_HXX | B13: 0 | D13: PS_SCK_SPO_HR_H_XX | E13: 0 | F13: BSC17_XX, | G13: 36 | H13: =IF(COUNTIF(Sheet2!A:A,A13)>0,VLOOKUP(A13,Sheet2!A:B,2,FALSE),"Not Found") -> 0 | I13: =IF(B13=H13,"Match","Mis Match") -> Match
... A358: PS_VISAPMTSUP_H_XX | B358: 0 | D358: PS_PERSNIDEXP_H_XX | E358: 0 | F358: PSPER_XX, | G358: 79 | H358: =IF(COUNTIF(Sheet2!A:A,A358)>0,VLOOKUP(A358,Sheet2!A:B,2,FALSE),"Not Found") -> 0 | I358: =IF(B358=H358,"Match","Mis Match") -> Match
A359: (blank) | D359: PS_PERX33700T_H_XX | E359: 0 | F359: PSPER_XX, | G359: 79 | H359: =IF(COUNTIF(Sheet2!A:A,A359)>0,VLOOKUP(A359,Sheet2!A:B,2,FALSE),"Not Found") -> 0 | I359: =IF(B359=H359,"Match","Mis Match") -> Match
A360: Grand Total | B360: 136326574 | D360: PS_PRIORWORKE_H_XX | E360: 0 | F360: PSPER_XX, | G360: 79
D361: PS_TAX_DISTRIB_H | E361: 0 | F361: PSPER_XX, | G361: 79
D362: PS_PERSDATAXX_H_XX | E362: 0 | F362: PSPER_XX, | G362: 79
D363: PS_PRIORWORKS_H_XX | E363: 0 | F363: PSPER_XX, | G363: 79
D364: PS_EOAW_HISCOM_HXX | E364: 0 | F364: TLEOA_XX, | G364: 62
D365: PS_TL_MEALAUD_H_XX | E365: 0 | F365: TLMEL_XX, | G365: 53
D366: PS_OB_ATTACH_H_XX | E366: 0 | F366: TLOB_XX, | G366: 54
D367: PS_TL_EXCEPTN_HST | E367: 0 | F367: TLEXCPXX, | G367: 56
D368: PS_TL_RTS_TRC_H_XX | E368: 0 | F368: TLRTS_XX, | G368: 55
D369: PS_TLTRCOMNT_H_XX | E369: 0 | F369: TLTRC_XX, | G369: 60

Sheet Sheet2
A1: table name | B1: Prd Exp Count
A2: PS_ADD_PAY_EFFDT_H | B2: 0
A3: PS_ADD_PAY_ERNCD_H | B3: 0
A4: PS_ADD_PY_DRW_H_XX | B4: 0
A5: PS_ADDL_PAY_DATA_H | B5: 0
A6: PS_ADDRESSES_H_XX | B6: 0
A7: PS_AUDITTLRTS_H_XX | B7: 0
A8: PS_BAL_ADJ_CHK_H | B8: 54
A9: PS_BAL_ADJ_DED_H | B9: 18
A10: PS_BAL_ADJ_ERN_H | B10: 40
A11: PS_BAL_ADJ_TAX_H | B11: 183
A12: PS_BEN_LVSP_H_XX | B12: 481505
A13: PS_BEN_PRGPRTC_HXX | B13: 0
... A357: PS_VISAPMTSUP_H_XX | B357: 0
A358: (blank)
A359: Grand Total | B359: 136326574

Sheet Sheet4
A1: Table Name | B1: Count
A2: PS_EOAWSTPINST_HXX | B2: 0
A3: PS_EOAW_COMNTS_HXX | B3: 0
A4: PS_EOAW_HISCOM_HXX | B4: 0
A5: PS_EOAW_SUMDTL_HXX | B5: 0
A6: PS_EOAW_SUMM_HXX | B6: 0
A7: PS_EOAW_WL_HXX | B7: 0
A8: PS_GP_ABSSXREF_HXX | B8: 0
A9: PS_GP_ABS_FCST_HXX | B9: 0
A10: PS_GP_ABSINTLG_HXX | B10: 0
A11: PS_GP_ABS_OVRD_HXX | B11: 0
A12: PS_GP_ABSSSDAT_HXX | B12: 0
A13: PS_GP_ABSSSSTA_HXX | B13: 0
... A367: PS_TL_XREF_TBL_HST | B367: 0
