Workbook

Sheet Delete log
A1: Table name | B1: Count | C1: Template | D1: batch no.
A2: PS_BL_ADJ_CN_CHK_H | B2: 0 | C2: ADJ_C_XX | D2: 5
A3: PS_FSA_BENEFIT_H | B3: 0 | C3: BEN3_XX | D3: 9
A4: PS_BN_EROR_WK_H_XX | B4: 2343 | C4: BEN5_XX | D4: 11
A5: PS_LIFE_AD_BNEFC_H | B5: 0 | C5: BEN9_XX | D5: 15
A6: PS_BENX74_AUD_H_XX | B6: 0 | C6: BENX_74 | D6: 17
A7: PS_SCK_SA_PRO_H_XX | B7: 0 | C7: BSC16_XX | D7: 35
A8: PS_SCK_SPO_HR_H_XX | B8: 0 | C8: BSC17_XX | D8: 36
A9: PS_CA_BPLINES_H_XX | B9: 1 | C9: CONTRCTS | D9: 85
A10: PS_CAN_EN_BALNCE_H | B10: 0 | C10: EECAN_XX | D10: 4
A11: PS_EOAW_UINST_HXX | B11: 0 | C11: EOUINSTX | D11: 84
A12: PS_GP_PIMNLDTA_HXX | B12: 0 | C12: GPARC6XX | D12: 67
A13: PS_FINAL_HRS0_H_XX | B13: 0 | C13: HRFL_XX | D13: 100
... A369: PS_TRNX0004_H_XX | B369: 0 | C369: PSPER_XX | D369: 79

Sheet Sheet2
A1: Table name | B1: Deleted count | D1: PRD EXP Count | F1: Count Compare
A2: PS_ADD_PAY_EFFDT_H | B2: 0 | D2: =IF(COUNTIF(Sheet4!A:A,A2)>0,VLOOKUP(A2,Sheet4!A:B,2,FALSE),"Not Found") -> 0 | F2: =IF(B2=D2,"Matching","Mis Match") -> Matching
A3: PS_ADD_PAY_ERNCD_H | B3: 0 | D3: =IF(COUNTIF(Sheet4!A:A,A3)>0,VLOOKUP(A3,Sheet4!A:B,2,FALSE),"Not Found") -> 0 | F3: =IF(B3=D3,"Matching","Mis Match") -> Matching
A4: PS_ADD_PY_DRW_H_XX | B4: 0 | D4: =IF(COUNTIF(Sheet4!A:A,A4)>0,VLOOKUP(A4,Sheet4!A:B,2,FALSE),"Not Found") -> 0 | F4: =IF(B4=D4,"Matching","Mis Match") -> Matching
A5: PS_ADDL_PAY_DATA_H | B5: 0 | D5: =IF(COUNTIF(Sheet4!A:A,A5)>0,VLOOKUP(A5,Sheet4!A:B,2,FALSE),"Not Found") -> 0 | F5: =IF(B5=D5,"Matching","Mis Match") -> Matching
A6: PS_ADDRESSES_H_XX | B6: 0 | D6: =IF(COUNTIF(Sheet4!A:A,A6)>0,VLOOKUP(A6,Sheet4!A:B,2,FALSE),"Not Found") -> 0 | F6: =IF(B6=D6,"Matching","Mis Match") -> Matching
A7: PS_AUDITTLRTS_H_XX | B7: 0 | D7: =IF(COUNTIF(Sheet4!A:A,A7)>0,VLOOKUP(A7,Sheet4!A:B,2,FALSE),"Not Found") -> 0 | F7: =IF(B7=D7,"Matching","Mis Match") -> Matching
A8: PS_BAL_ADJ_CHK_H | B8: 54 | D8: =IF(COUNTIF(Sheet4!A:A,A8)>0,VLOOKUP(A8,Sheet4!A:B,2,FALSE),"Not Found") -> 54 | F8: =IF(B8=D8,"Matching","Mis Match") -> Matching
A9: PS_BAL_ADJ_DED_H | B9: 18 | D9: =IF(COUNTIF(Sheet4!A:A,A9)>0,VLOOKUP(A9,Sheet4!A:B,2,FALSE),"Not Found") -> 18 | F9: =IF(B9=D9,"Matching","Mis Match") -> Matching
A10: PS_BAL_ADJ_ERN_H | B10: 40 | D10: =IF(COUNTIF(Sheet4!A:A,A10)>0,VLOOKUP(A10,Sheet4!A:B,2,FALSE),"Not Found") -> 40 | F10: =IF(B10=D10,"Matching","Mis Match") -> Matching
A11: PS_BAL_ADJ_TAX_H | B11: 183 | D11: =IF(COUNTIF(Sheet4!A:A,A11)>0,VLOOKUP(A11,Sheet4!A:B,2,FALSE),"Not Found") -> 183 | F11: =IF(B11=D11,"Matching","Mis Match") -> Matching
A12: PS_BEN_LVSP_H_XX | B12: 481505 | D12: =IF(COUNTIF(Sheet4!A:A,A12)>0,VLOOKUP(A12,Sheet4!A:B,2,FALSE),"Not Found") -> 481505 | F12: =IF(B12=D12,"Matching","Mis Match") -> Matching
A13: PS_BEN_PRGPRTC_HXX | B13: 0 | D13: =IF(COUNTIF(Sheet4!A:A,A13)>0,VLOOKUP(A13,Sheet4!A:B,2,FALSE),"Not Found") -> 0 | F13: =IF(B13=D13,"Matching","Mis Match") -> Matching
... A358: PS_VISAPMTSUP_H_XX | B358: 0 | D358: =IF(COUNTIF(Sheet4!A:A,A358)>0,VLOOKUP(A358,Sheet4!A:B,2,FALSE),"Not Found") -> 0 | F358: =IF(B358=D358,"Matching","Mis Match") -> Matching
A359: (blank) | D359: =IF(COUNTIF(Sheet4!A:A,A359)>0,VLOOKUP(A359,Sheet4!A:B,2,FALSE),"Not Found") -> 0 | F359: =IF(B359=D359,"Matching","Mis Match") -> Matching
A360: Grand Total | B360: 136326574

Sheet Sheet3
A1: PRD EXP Table name | B1: Count
A2: PS_EOAWSTPINST_HXX | B2: 0
A3: PS_EOAW_COMNTS_HXX | B3: 0
A4: PS_EOAW_HISCOM_HXX | B4: 0
A5: PS_EOAW_SUMDTL_HXX | B5: 0
A6: PS_EOAW_SUMM_HXX | B6: 0
A7: PS_EOAW_WL_HXX | B7: 0
A8: PS_GP_ABSSXREF_HXX | B8: 0
A9: PS_GP_ABS_FCST_HXX | B9: 0
A10: PS_GP_ABSINTLG_HXX | B10: 0
A11: PS_GP_ABS_OVRD_HXX | B11: 0
A12: PS_GP_ABSSSDAT_HXX | B12: 0
A13: PS_GP_ABSSSSTA_HXX | B13: 0
... A367: PS_TL_XREF_TBL_HST | B367: 0

Sheet Sheet4
A1: Row Labels | B1: Sum of Count
A2: PS_ADD_PAY_EFFDT_H | B2: 0
A3: PS_ADD_PAY_ERNCD_H | B3: 0
A4: PS_ADD_PY_DRW_H_XX | B4: 0
A5: PS_ADDL_PAY_DATA_H | B5: 0
A6: PS_ADDRESSES_H_XX | B6: 0
A7: PS_AUDITTLRTS_H_XX | B7: 0
A8: PS_BAL_ADJ_CHK_H | B8: 54
A9: PS_BAL_ADJ_DED_H | B9: 18
A10: PS_BAL_ADJ_ERN_H | B10: 40
A11: PS_BAL_ADJ_TAX_H | B11: 183
A12: PS_BEN_LVSP_H_XX | B12: 481505
A13: PS_BEN_PRGPRTC_HXX | B13: 0
... A357: PS_VISAPMTSUP_H_XX | B357: 0
A358: (blank)
A359: Grand Total | B359: 50563415
